brkMatematik/__init__.py
burakmatematik-1.0.dist-info/licenses/LICENSE
burakmatematik-1.0.dist-info/METADATA
burakmatematik-1.0.dist-info/WHEEL
burakmatematik-1.0.dist-info/top_level.txt
burakmatematik-1.0.dist-info/RECORD
